{
  "7.3 Safe to vaccinate" : {
    "transaction" : "7.3 Safe to vaccinate",
    "sampleCount" : 27,
    "errorCount" : 0,
    "errorPct" : 0.0,
    "meanResTime" : 201.66666666666666,
    "medianResTime" : 104.0,
    "minResTime" : 88.0,
    "maxResTime" : 2466.0,
    "pct1ResTime" : 238.6,
    "pct2ResTime" : 1582.3999999999953,
    "pct3ResTime" : 2466.0,
    "throughput" : 0.007837745887505704,
    "receivedKBytesPerSec" : 3.368110560132493,
    "sentKBytesPerSec" : 0.03445115676420693
  },
  "2.0 Register attendance" : {
    "transaction" : "2.0 Register attendance",
    "sampleCount" : 1615,
    "errorCount" : 18,
    "errorPct" : 1.1145511,
    "meanResTime" : 1354.0241486068112,
    "medianResTime" : 1254.0,
    "minResTime" : 346.0,
    "maxResTime" : 4685.0,
    "pct1ResTime" : 1958.4000000000005,
    "pct2ResTime" : 2304.7999999999993,
    "pct3ResTime" : 2925.5199999999995,
    "throughput" : 0.4535248003648418,
    "receivedKBytesPerSec" : 985.9033779739046,
    "sentKBytesPerSec" : 9.800943912970556
  },
  "2.5 Select patient" : {
    "transaction" : "2.5 Select patient",
    "sampleCount" : 1612,
    "errorCount" : 0,
    "errorPct" : 0.0,
    "meanResTime" : 107.91811414392086,
    "medianResTime" : 85.0,
    "minResTime" : 58.0,
    "maxResTime" : 1343.0,
    "pct1ResTime" : 162.70000000000005,
    "pct2ResTime" : 246.69999999999982,
    "pct3ResTime" : 504.8699999999999,
    "throughput" : 0.4540765766907733,
    "receivedKBytesPerSec" : 191.43465619403267,
    "sentKBytesPerSec" : 1.8955646606488845
  },
  "7.1 Full name search" : {
    "transaction" : "7.1 Full name search",
    "sampleCount" : 27,
    "errorCount" : 0,
    "errorPct" : 0.0,
    "meanResTime" : 732.9629629629628,
    "medianResTime" : 650.0,
    "minResTime" : 299.0,
    "maxResTime" : 1687.0,
    "pct1ResTime" : 1312.6,
    "pct2ResTime" : 1606.9999999999995,
    "pct3ResTime" : 1687.0,
    "throughput" : 0.007782818994690387,
    "receivedKBytesPerSec" : 3.342490493971198,
    "sentKBytesPerSec" : 0.03379958259228406
  },
  "2.3 Search by first/last name" : {
    "transaction" : "2.3 Search by first/last name",
    "sampleCount" : 1620,
    "errorCount" : 0,
    "errorPct" : 0.0,
    "meanResTime" : 104.53641975308658,
    "medianResTime" : 82.0,
    "minResTime" : 58.0,
    "maxResTime" : 1364.0,
    "pct1ResTime" : 153.0,
    "pct2ResTime" : 223.94999999999982,
    "pct3ResTime" : 516.3699999999999,
    "throughput" : 0.4535921982141907,
    "receivedKBytesPerSec" : 192.99740767115057,
    "sentKBytesPerSec" : 1.9678384188041966
  },
  "4.0 Vaccination for flu" : {
    "transaction" : "4.0 Vaccination for flu",
    "sampleCount" : 408,
    "errorCount" : 0,
    "errorPct" : 0.0,
    "meanResTime" : 996.4705882352946,
    "medianResTime" : 863.5,
    "minResTime" : 170.0,
    "maxResTime" : 4687.0,
    "pct1ResTime" : 1448.2000000000007,
    "pct2ResTime" : 1838.4999999999995,
    "pct3ResTime" : 3022.3599999999874,
    "throughput" : 0.11667546975460118,
    "receivedKBytesPerSec" : 143.71283577754264,
    "sentKBytesPerSec" : 1.968121073105475
  },
  "4.0 Vaccination for hpv" : {
    "transaction" : "4.0 Vaccination for hpv",
    "sampleCount" : 406,
    "errorCount" : 0,
    "errorPct" : 0.0,
    "meanResTime" : 964.583743842364,
    "medianResTime" : 862.0,
    "minResTime" : 194.0,
    "maxResTime" : 4691.0,
    "pct1ResTime" : 1325.0,
    "pct2ResTime" : 1571.1999999999998,
    "pct3ResTime" : 2432.0,
    "throughput" : 0.11611555156173986,
    "receivedKBytesPerSec" : 142.90326859781106,
    "sentKBytesPerSec" : 1.9631056352829117
  },
  "7.6 First name search" : {
    "transaction" : "7.6 First name search",
    "sampleCount" : 27,
    "errorCount" : 0,
    "errorPct" : 0.0,
    "meanResTime" : 1739.7037037037035,
    "medianResTime" : 1002.0,
    "minResTime" : 600.0,
    "maxResTime" : 9408.0,
    "pct1ResTime" : 3594.1999999999985,
    "pct2ResTime" : 7749.999999999991,
    "pct3ResTime" : 9408.0,
    "throughput" : 0.00784425151459423,
    "receivedKBytesPerSec" : 4.053112671179,
    "sentKBytesPerSec" : 0.03400565877404227
  },
  "1.2 Sign-in page" : {
    "transaction" : "1.2 Sign-in page",
    "sampleCount" : 1652,
    "errorCount" : 0,
    "errorPct" : 0.0,
    "meanResTime" : 145.49757869249405,
    "medianResTime" : 99.0,
    "minResTime" : 12.0,
    "maxResTime" : 4930.0,
    "pct1ResTime" : 228.70000000000005,
    "pct2ResTime" : 361.0,
    "pct3ResTime" : 881.9400000000028,
    "throughput" : 0.4597679396468303,
    "receivedKBytesPerSec" : 192.6119563938149,
    "sentKBytesPerSec" : 2.2940956561009562
  },
  "2.4 Patient attending session" : {
    "transaction" : "2.4 Patient attending session",
    "sampleCount" : 1496,
    "errorCount" : 18,
    "errorPct" : 1.2032086,
    "meanResTime" : 798.4525401069513,
    "medianResTime" : 688.0,
    "minResTime" : 30.0,
    "maxResTime" : 4045.0,
    "pct1ResTime" : 1203.0,
    "pct2ResTime" : 1452.9999999999973,
    "pct3ResTime" : 2011.6699999999976,
    "throughput" : 0.42055395614488084,
    "receivedKBytesPerSec" : 215.55945113096615,
    "sentKBytesPerSec" : 2.1486366442282203
  },
  "Check STS status" : {
    "transaction" : "Check STS status",
    "sampleCount" : 1,
    "errorCount" : 0,
    "errorPct" : 0.0,
    "meanResTime" : 28.0,
    "medianResTime" : 28.0,
    "minResTime" : 28.0,
    "maxResTime" : 28.0,
    "pct1ResTime" : 28.0,
    "pct2ResTime" : 28.0,
    "pct3ResTime" : 28.0,
    "throughput" : 35.714285714285715,
    "receivedKBytesPerSec" : 11.160714285714285,
    "sentKBytesPerSec" : 21.065848214285715
  },
  "1.1 Homepage" : {
    "transaction" : "1.1 Homepage",
    "sampleCount" : 1655,
    "errorCount" : 0,
    "errorPct" : 0.0,
    "meanResTime" : 147.17583081570984,
    "medianResTime" : 104.0,
    "minResTime" : 23.0,
    "maxResTime" : 4977.0,
    "pct1ResTime" : 218.0,
    "pct2ResTime" : 328.1999999999989,
    "pct3ResTime" : 871.7200000000007,
    "throughput" : 0.4597438046397178,
    "receivedKBytesPerSec" : 192.40131407384123,
    "sentKBytesPerSec" : 2.2855424063657432
  },
  "1.3 Sign-in" : {
    "transaction" : "1.3 Sign-in",
    "sampleCount" : 1650,
    "errorCount" : 0,
    "errorPct" : 0.0,
    "meanResTime" : 167.04969696969687,
    "medianResTime" : 105.0,
    "minResTime" : 65.0,
    "maxResTime" : 5305.0,
    "pct1ResTime" : 320.9000000000001,
    "pct2ResTime" : 451.34999999999945,
    "pct3ResTime" : 899.3100000000002,
    "throughput" : 0.45926487558932033,
    "receivedKBytesPerSec" : 192.59859523139016,
    "sentKBytesPerSec" : 2.4041428962300757
  },
  "Run some searches" : {
    "transaction" : "Run some searches",
    "sampleCount" : 27,
    "errorCount" : 0,
    "errorPct" : 0.0,
    "meanResTime" : 10913.592592592593,
    "medianResTime" : 8303.0,
    "minResTime" : 6587.0,
    "maxResTime" : 52492.0,
    "pct1ResTime" : 15174.0,
    "pct2ResTime" : 37612.799999999916,
    "pct3ResTime" : 52492.0,
    "throughput" : 0.007762961702147235,
    "receivedKBytesPerSec" : 30.966145654383887,
    "sentKBytesPerSec" : 0.2714108076851308
  },
  "4.0 Vaccination for td_ipv" : {
    "transaction" : "4.0 Vaccination for td_ipv",
    "sampleCount" : 388,
    "errorCount" : 0,
    "errorPct" : 0.0,
    "meanResTime" : 982.7268041237114,
    "medianResTime" : 876.0,
    "minResTime" : 167.0,
    "maxResTime" : 3659.0,
    "pct1ResTime" : 1420.2,
    "pct2ResTime" : 1779.8999999999992,
    "pct3ResTime" : 2704.6500000000015,
    "throughput" : 0.11190908828704103,
    "receivedKBytesPerSec" : 138.05842328603157,
    "sentKBytesPerSec" : 1.8868688213853078
  },
  "2.1 Open session" : {
    "transaction" : "2.1 Open session",
    "sampleCount" : 1620,
    "errorCount" : 0,
    "errorPct" : 0.0,
    "meanResTime" : 282.9308641975309,
    "medianResTime" : 221.0,
    "minResTime" : 78.0,
    "maxResTime" : 1853.0,
    "pct1ResTime" : 492.60000000000036,
    "pct2ResTime" : 651.8499999999995,
    "pct3ResTime" : 1249.79,
    "throughput" : 0.4534137013783776,
    "receivedKBytesPerSec" : 190.40037309938842,
    "sentKBytesPerSec" : 1.89619901474882
  },
  "7.7 Partial name search" : {
    "transaction" : "7.7 Partial name search",
    "sampleCount" : 27,
    "errorCount" : 0,
    "errorPct" : 0.0,
    "meanResTime" : 1210.111111111111,
    "medianResTime" : 785.0,
    "minResTime" : 235.0,
    "maxResTime" : 6603.0,
    "pct1ResTime" : 2612.0,
    "pct2ResTime" : 5083.399999999992,
    "pct3ResTime" : 6603.0,
    "throughput" : 0.007890528560206486,
    "receivedKBytesPerSec" : 4.060337056804354,
    "sentKBytesPerSec" : 0.03419856905995165
  },
  "4.3 Vaccination confirm" : {
    "transaction" : "4.3 Vaccination confirm",
    "sampleCount" : 1557,
    "errorCount" : 0,
    "errorPct" : 0.0,
    "meanResTime" : 730.626204238921,
    "medianResTime" : 616.0,
    "minResTime" : 433.0,
    "maxResTime" : 5750.0,
    "pct1ResTime" : 1067.2,
    "pct2ResTime" : 1379.6999999999994,
    "pct3ResTime" : 2193.0800000000017,
    "throughput" : 0.4499919365606743,
    "receivedKBytesPerSec" : 188.45290216936505,
    "sentKBytesPerSec" : 2.7247815460929603
  },
  "4.1 Vaccination questions" : {
    "transaction" : "4.1 Vaccination questions",
    "sampleCount" : 1597,
    "errorCount" : 0,
    "errorPct" : 0.0,
    "meanResTime" : 134.14214151534136,
    "medianResTime" : 106.0,
    "minResTime" : 74.0,
    "maxResTime" : 1187.0,
    "pct1ResTime" : 200.0,
    "pct2ResTime" : 276.1999999999998,
    "pct3ResTime" : 518.1599999999999,
    "throughput" : 0.4546271047142582,
    "receivedKBytesPerSec" : 186.27466651619778,
    "sentKBytesPerSec" : 2.605721540916155
  },
  "7.7 Last name search" : {
    "transaction" : "7.7 Last name search",
    "sampleCount" : 27,
    "errorCount" : 0,
    "errorPct" : 0.0,
    "meanResTime" : 1613.5555555555557,
    "medianResTime" : 910.0,
    "minResTime" : 359.0,
    "maxResTime" : 11224.0,
    "pct1ResTime" : 3318.0,
    "pct2ResTime" : 8112.799999999984,
    "pct3ResTime" : 11224.0,
    "throughput" : 0.007866880723519935,
    "receivedKBytesPerSec" : 4.066271652587621,
    "sentKBytesPerSec" : 0.034139894991710634
  },
  "Reset counters" : {
    "transaction" : "Reset counters",
    "sampleCount" : 1,
    "errorCount" : 0,
    "errorPct" : 0.0,
    "meanResTime" : 35.0,
    "medianResTime" : 35.0,
    "minResTime" : 35.0,
    "maxResTime" : 35.0,
    "pct1ResTime" : 35.0,
    "pct2ResTime" : 35.0,
    "pct3ResTime" : 35.0,
    "throughput" : 28.57142857142857,
    "receivedKBytesPerSec" : 0.0,
    "sentKBytesPerSec" : 0.0
  },
  "1.0 Login" : {
    "transaction" : "1.0 Login",
    "sampleCount" : 1650,
    "errorCount" : 0,
    "errorPct" : 0.0,
    "meanResTime" : 804.6454545454552,
    "medianResTime" : 678.0,
    "minResTime" : 411.0,
    "maxResTime" : 15212.0,
    "pct1ResTime" : 1161.6000000000004,
    "pct2ResTime" : 1409.4499999999998,
    "pct3ResTime" : 2294.92,
    "throughput" : 0.45945900790269495,
    "receivedKBytesPerSec" : 793.3511979566953,
    "sentKBytesPerSec" : 8.866738700789156
  },
  "4.0 Vaccination for menacwy" : {
    "transaction" : "4.0 Vaccination for menacwy",
    "sampleCount" : 389,
    "errorCount" : 0,
    "errorPct" : 0.0,
    "meanResTime" : 968.529562982005,
    "medianResTime" : 878.0,
    "minResTime" : 177.0,
    "maxResTime" : 5933.0,
    "pct1ResTime" : 1370.0,
    "pct2ResTime" : 1593.5,
    "pct3ResTime" : 2356.9000000000096,
    "throughput" : 0.11162805646370925,
    "receivedKBytesPerSec" : 137.5002335486179,
    "sentKBytesPerSec" : 1.8841160633526526
  },
  "7.0 Open Children Search" : {
    "transaction" : "7.0 Open Children Search",
    "sampleCount" : 27,
    "errorCount" : 0,
    "errorPct" : 0.0,
    "meanResTime" : 1018.1111111111114,
    "medianResTime" : 637.0,
    "minResTime" : 224.0,
    "maxResTime" : 5019.0,
    "pct1ResTime" : 2675.0,
    "pct2ResTime" : 4180.599999999996,
    "pct3ResTime" : 5019.0,
    "throughput" : 0.00778027803255787,
    "receivedKBytesPerSec" : 3.9654823192461315,
    "sentKBytesPerSec" : 0.032473824677341785
  },
  "Initialise vaccination list" : {
    "transaction" : "Initialise vaccination list",
    "sampleCount" : 1,
    "errorCount" : 0,
    "errorPct" : 0.0,
    "meanResTime" : 43.0,
    "medianResTime" : 43.0,
    "minResTime" : 43.0,
    "maxResTime" : 43.0,
    "pct1ResTime" : 43.0,
    "pct2ResTime" : 43.0,
    "pct3ResTime" : 43.0,
    "throughput" : 23.25581395348837,
    "receivedKBytesPerSec" : 6.6542514534883725,
    "sentKBytesPerSec" : 14.353197674418606
  },
  "7.5 year group" : {
    "transaction" : "7.5 year group",
    "sampleCount" : 27,
    "errorCount" : 0,
    "errorPct" : 0.0,
    "meanResTime" : 1856.8888888888887,
    "medianResTime" : 1739.0,
    "minResTime" : 1544.0,
    "maxResTime" : 3364.0,
    "pct1ResTime" : 2390.1999999999994,
    "pct2ResTime" : 3291.5999999999995,
    "pct3ResTime" : 3364.0,
    "throughput" : 0.007838282870274677,
    "receivedKBytesPerSec" : 4.052989300635017,
    "sentKBytesPerSec" : 0.034644881423472815
  },
  "7.2 No Consent search" : {
    "transaction" : "7.2 No Consent search",
    "sampleCount" : 27,
    "errorCount" : 0,
    "errorPct" : 0.0,
    "meanResTime" : 3143.296296296297,
    "medianResTime" : 2140.0,
    "minResTime" : 1949.0,
    "maxResTime" : 24807.0,
    "pct1ResTime" : 3960.999999999999,
    "pct2ResTime" : 16777.399999999958,
    "pct3ResTime" : 24807.0,
    "throughput" : 0.007780383405767743,
    "receivedKBytesPerSec" : 4.295767263410067,
    "sentKBytesPerSec" : 0.0343357820048953
  },
  "Total" : {
    "transaction" : "Total",
    "sampleCount" : 19539,
    "errorCount" : 18,
    "errorPct" : 0.09212345,
    "meanResTime" : 276.1842980705263,
    "medianResTime" : 124.0,
    "minResTime" : 2.0,
    "maxResTime" : 24807.0,
    "pct1ResTime" : 654.0,
    "pct2ResTime" : 848.0,
    "pct3ResTime" : 1616.9999999999927,
    "throughput" : 5.198479539849822,
    "receivedKBytesPerSec" : 2249.002787715915,
    "sentKBytesPerSec" : 25.21923363682186
  },
  "1.4 Open Sessions list" : {
    "transaction" : "1.4 Open Sessions list",
    "sampleCount" : 1622,
    "errorCount" : 0,
    "errorPct" : 0.0,
    "meanResTime" : 350.63933415536394,
    "medianResTime" : 301.5,
    "minResTime" : 209.0,
    "maxResTime" : 3065.0,
    "pct1ResTime" : 549.7,
    "pct2ResTime" : 656.8499999999999,
    "pct3ResTime" : 946.8499999999999,
    "throughput" : 0.45232553048554164,
    "receivedKBytesPerSec" : 216.22220495170964,
    "sentKBytesPerSec" : 1.8878021136109548
  },
  "Reset vaccination list" : {
    "transaction" : "Reset vaccination list",
    "sampleCount" : 1,
    "errorCount" : 0,
    "errorPct" : 0.0,
    "meanResTime" : 2.0,
    "medianResTime" : 2.0,
    "minResTime" : 2.0,
    "maxResTime" : 2.0,
    "pct1ResTime" : 2.0,
    "pct2ResTime" : 2.0,
    "pct3ResTime" : 2.0,
    "throughput" : 500.0,
    "receivedKBytesPerSec" : 142.578125,
    "sentKBytesPerSec" : 307.12890625
  },
  "4.2 Vaccination batch" : {
    "transaction" : "4.2 Vaccination batch",
    "sampleCount" : 1591,
    "errorCount" : 0,
    "errorPct" : 0.0,
    "meanResTime" : 128.9107479572595,
    "medianResTime" : 96.0,
    "minResTime" : 68.0,
    "maxResTime" : 1893.0,
    "pct1ResTime" : 200.79999999999995,
    "pct2ResTime" : 292.0,
    "pct3ResTime" : 546.5599999999995,
    "throughput" : 0.45406624743785057,
    "receivedKBytesPerSec" : 187.24667469963418,
    "sentKBytesPerSec" : 2.37084134332046
  },
  "2.2 Session register" : {
    "transaction" : "2.2 Session register",
    "sampleCount" : 1620,
    "errorCount" : 0,
    "errorPct" : 0.0,
    "meanResTime" : 118.9759259259261,
    "medianResTime" : 81.0,
    "minResTime" : 57.0,
    "maxResTime" : 1548.0,
    "pct1ResTime" : 233.80000000000018,
    "pct2ResTime" : 324.9499999999998,
    "pct3ResTime" : 529.0599999999995,
    "throughput" : 0.45357937121019737,
    "receivedKBytesPerSec" : 196.32352007349456,
    "sentKBytesPerSec" : 1.900878391800741
  },
  "7.3 Due vaccination" : {
    "transaction" : "7.3 Due vaccination",
    "sampleCount" : 27,
    "errorCount" : 0,
    "errorPct" : 0.0,
    "meanResTime" : 415.40740740740745,
    "medianResTime" : 351.0,
    "minResTime" : 302.0,
    "maxResTime" : 1076.0,
    "pct1ResTime" : 854.4,
    "pct2ResTime" : 1021.5999999999997,
    "pct3ResTime" : 1076.0,
    "throughput" : 0.007838933719202426,
    "receivedKBytesPerSec" : 4.016585090192013,
    "sentKBytesPerSec" : 0.034349205008730246
  }
}