{
  "2.0 Register attendance" : {
    "transaction" : "2.0 Register attendance",
    "sampleCount" : 1617,
    "errorCount" : 4,
    "errorPct" : 0.24737167,
    "meanResTime" : 1118.4718614718613,
    "medianResTime" : 1075.0,
    "minResTime" : 425.0,
    "maxResTime" : 3886.0,
    "pct1ResTime" : 1454.0,
    "pct2ResTime" : 1591.2999999999997,
    "pct3ResTime" : 2063.64,
    "throughput" : 0.45287001118311665,
    "receivedKBytesPerSec" : 70.75209276243635,
    "sentKBytesPerSec" : 16.912158223350616
  },
  "2.5 Select patient" : {
    "transaction" : "2.5 Select patient",
    "sampleCount" : 1612,
    "errorCount" : 0,
    "errorPct" : 0.0,
    "meanResTime" : 133.99069478908223,
    "medianResTime" : 106.0,
    "minResTime" : 58.0,
    "maxResTime" : 1845.0,
    "pct1ResTime" : 220.0,
    "pct2ResTime" : 305.3499999999999,
    "pct3ResTime" : 545.189999999996,
    "throughput" : 0.4549822960517867,
    "receivedKBytesPerSec" : 11.512838350304616,
    "sentKBytesPerSec" : 3.2811587107094424
  },
  "7.1 Full name search" : {
    "transaction" : "7.1 Full name search",
    "sampleCount" : 194,
    "errorCount" : 0,
    "errorPct" : 0.0,
    "meanResTime" : 538.5979381443296,
    "medianResTime" : 317.5,
    "minResTime" : 185.0,
    "maxResTime" : 4494.0,
    "pct1ResTime" : 1107.0,
    "pct2ResTime" : 2114.25,
    "pct3ResTime" : 3972.450000000006,
    "throughput" : 0.05483441701969856,
    "receivedKBytesPerSec" : 2.281228617845522,
    "sentKBytesPerSec" : 0.40464810940328283
  },
  "2.3 Search by first/last name" : {
    "transaction" : "2.3 Search by first/last name",
    "sampleCount" : 1623,
    "errorCount" : 0,
    "errorPct" : 0.0,
    "meanResTime" : 119.87122612446099,
    "medianResTime" : 101.0,
    "minResTime" : 61.0,
    "maxResTime" : 858.0,
    "pct1ResTime" : 180.60000000000014,
    "pct2ResTime" : 233.0,
    "pct3ResTime" : 407.76,
    "throughput" : 0.4547987998691928,
    "receivedKBytesPerSec" : 14.274794170617083,
    "sentKBytesPerSec" : 3.401072158222065
  },
  "4.0 Vaccination for flu" : {
    "transaction" : "4.0 Vaccination for flu",
    "sampleCount" : 406,
    "errorCount" : 2,
    "errorPct" : 0.49261084,
    "meanResTime" : 915.9999999999997,
    "medianResTime" : 867.0,
    "minResTime" : 213.0,
    "maxResTime" : 3009.0,
    "pct1ResTime" : 1181.6,
    "pct2ResTime" : 1330.25,
    "pct3ResTime" : 2049.04,
    "throughput" : 0.11664082469085153,
    "receivedKBytesPerSec" : 6.155443564981724,
    "sentKBytesPerSec" : 3.3133028954827823
  },
  "4.0 Vaccination for hpv" : {
    "transaction" : "4.0 Vaccination for hpv",
    "sampleCount" : 408,
    "errorCount" : 5,
    "errorPct" : 1.2254902,
    "meanResTime" : 904.3137254901961,
    "medianResTime" : 855.0,
    "minResTime" : 221.0,
    "maxResTime" : 2073.0,
    "pct1ResTime" : 1190.2,
    "pct2ResTime" : 1367.7499999999998,
    "pct3ResTime" : 1832.0999999999997,
    "throughput" : 0.11689810868601655,
    "receivedKBytesPerSec" : 5.731391503924969,
    "sentKBytesPerSec" : 3.317969848382007
  },
  "1.2 Sign-in page" : {
    "transaction" : "1.2 Sign-in page",
    "sampleCount" : 3330,
    "errorCount" : 0,
    "errorPct" : 0.0,
    "meanResTime" : 732.0330330330338,
    "medianResTime" : 226.0,
    "minResTime" : 12.0,
    "maxResTime" : 9048.0,
    "pct1ResTime" : 1882.4000000000015,
    "pct2ResTime" : 3697.45,
    "pct3ResTime" : 4733.7400000000025,
    "throughput" : 0.9260479776280157,
    "receivedKBytesPerSec" : 64.49122692944738,
    "sentKBytesPerSec" : 8.042902340210839
  },
  "7.7 Due vaccination search" : {
    "transaction" : "7.7 Due vaccination search",
    "sampleCount" : 186,
    "errorCount" : 0,
    "errorPct" : 0.0,
    "meanResTime" : 719.833333333333,
    "medianResTime" : 665.0,
    "minResTime" : 529.0,
    "maxResTime" : 3172.0,
    "pct1ResTime" : 934.3000000000002,
    "pct2ResTime" : 1026.0000000000002,
    "pct3ResTime" : 1503.3399999999913,
    "throughput" : 0.05425698558689431,
    "receivedKBytesPerSec" : 7.263093896125584,
    "sentKBytesPerSec" : 0.4110232154629492
  },
  "7.2 First name search" : {
    "transaction" : "7.2 First name search",
    "sampleCount" : 197,
    "errorCount" : 0,
    "errorPct" : 0.0,
    "meanResTime" : 1173.8477157360398,
    "medianResTime" : 667.0,
    "minResTime" : 252.0,
    "maxResTime" : 8952.0,
    "pct1ResTime" : 2742.000000000005,
    "pct2ResTime" : 4831.5,
    "pct3ResTime" : 5723.880000000034,
    "throughput" : 0.058995265704794284,
    "receivedKBytesPerSec" : 7.993317763755255,
    "sentKBytesPerSec" : 0.43493567120291343
  },
  "2.4 Patient attending session" : {
    "transaction" : "2.4 Patient attending session",
    "sampleCount" : 1517,
    "errorCount" : 4,
    "errorPct" : 0.2636783,
    "meanResTime" : 451.2643375082399,
    "medianResTime" : 413.0,
    "minResTime" : 120.0,
    "maxResTime" : 3085.0,
    "pct1ResTime" : 616.0,
    "pct2ResTime" : 733.3999999999996,
    "pct3ResTime" : 1004.0,
    "throughput" : 0.4266151616272458,
    "receivedKBytesPerSec" : 13.908898955077591,
    "sentKBytesPerSec" : 3.7429188070074
  },
  "Check STS status" : {
    "transaction" : "Check STS status",
    "sampleCount" : 1,
    "errorCount" : 0,
    "errorPct" : 0.0,
    "meanResTime" : 19.0,
    "medianResTime" : 19.0,
    "minResTime" : 19.0,
    "maxResTime" : 19.0,
    "pct1ResTime" : 19.0,
    "pct2ResTime" : 19.0,
    "pct3ResTime" : 19.0,
    "throughput" : 52.63157894736842,
    "receivedKBytesPerSec" : 16.49876644736842,
    "sentKBytesPerSec" : 31.044407894736842
  },
  "1.1 Homepage" : {
    "transaction" : "1.1 Homepage",
    "sampleCount" : 3332,
    "errorCount" : 0,
    "errorPct" : 0.0,
    "meanResTime" : 733.599939975991,
    "medianResTime" : 235.0,
    "minResTime" : 28.0,
    "maxResTime" : 8973.0,
    "pct1ResTime" : 1883.2000000000044,
    "pct2ResTime" : 3677.7,
    "pct3ResTime" : 4646.34,
    "throughput" : 0.9263007130180279,
    "receivedKBytesPerSec" : 74.94079867573679,
    "sentKBytesPerSec" : 8.032031255646904
  },
  "1.3 Sign-in" : {
    "transaction" : "1.3 Sign-in",
    "sampleCount" : 3328,
    "errorCount" : 0,
    "errorPct" : 0.0,
    "meanResTime" : 744.4002403846141,
    "medianResTime" : 267.0,
    "minResTime" : 50.0,
    "maxResTime" : 9612.0,
    "pct1ResTime" : 1915.199999999999,
    "pct2ResTime" : 3666.5499999999997,
    "pct3ResTime" : 4802.980000000001,
    "throughput" : 0.925663749305335,
    "receivedKBytesPerSec" : 64.71632216658722,
    "sentKBytesPerSec" : 8.295616840988881
  },
  "Run some searches" : {
    "transaction" : "Run some searches",
    "sampleCount" : 1680,
    "errorCount" : 1,
    "errorPct" : 0.05952381,
    "meanResTime" : 1380.3404761904778,
    "medianResTime" : 829.5,
    "minResTime" : 0.0,
    "maxResTime" : 60006.0,
    "pct1ResTime" : 3672.9,
    "pct2ResTime" : 4019.749999999999,
    "pct3ResTime" : 5257.310000000003,
    "throughput" : 0.4702190409042984,
    "receivedKBytesPerSec" : 55.13852646603731,
    "sentKBytesPerSec" : 3.5148999040459272
  },
  "4.0 Vaccination for td_ipv" : {
    "transaction" : "4.0 Vaccination for td_ipv",
    "sampleCount" : 384,
    "errorCount" : 2,
    "errorPct" : 0.5208333,
    "meanResTime" : 903.7265624999995,
    "medianResTime" : 851.0,
    "minResTime" : 221.0,
    "maxResTime" : 1702.0,
    "pct1ResTime" : 1203.5,
    "pct2ResTime" : 1297.25,
    "pct3ResTime" : 1502.6499999999978,
    "throughput" : 0.11143370782604153,
    "receivedKBytesPerSec" : 5.57961607650693,
    "sentKBytesPerSec" : 3.1738208276927273
  },
  "2.1 Open session" : {
    "transaction" : "2.1 Open session",
    "sampleCount" : 1626,
    "errorCount" : 0,
    "errorPct" : 0.0,
    "meanResTime" : 302.5147601476015,
    "medianResTime" : 261.0,
    "minResTime" : 108.0,
    "maxResTime" : 2046.0,
    "pct1ResTime" : 487.0,
    "pct2ResTime" : 572.6499999999999,
    "pct3ResTime" : 769.2200000000003,
    "throughput" : 0.4541099040923234,
    "receivedKBytesPerSec" : 10.393620762129636,
    "sentKBytesPerSec" : 3.278039322887502
  },
  "4.3 Vaccination confirm" : {
    "transaction" : "4.3 Vaccination confirm",
    "sampleCount" : 1566,
    "errorCount" : 5,
    "errorPct" : 0.3192848,
    "meanResTime" : 616.2943805874836,
    "medianResTime" : 573.0,
    "minResTime" : 78.0,
    "maxResTime" : 2389.0,
    "pct1ResTime" : 849.3,
    "pct2ResTime" : 984.2499999999993,
    "pct3ResTime" : 1356.819999999996,
    "throughput" : 0.45263372999964446,
    "receivedKBytesPerSec" : 9.686902187830858,
    "sentKBytesPerSec" : 4.6530757266744045
  },
  "4.1 Vaccination questions" : {
    "transaction" : "4.1 Vaccination questions",
    "sampleCount" : 1583,
    "errorCount" : 0,
    "errorPct" : 0.0,
    "meanResTime" : 152.84586228679683,
    "medianResTime" : 123.0,
    "minResTime" : 71.0,
    "maxResTime" : 949.0,
    "pct1ResTime" : 254.0,
    "pct2ResTime" : 321.5999999999999,
    "pct3ResTime" : 503.32000000000016,
    "throughput" : 0.45177366111039285,
    "receivedKBytesPerSec" : 6.334005845642239,
    "sentKBytesPerSec" : 4.235830684906564
  },
  "Reset counters" : {
    "transaction" : "Reset counters",
    "sampleCount" : 1,
    "errorCount" : 0,
    "errorPct" : 0.0,
    "meanResTime" : 21.0,
    "medianResTime" : 21.0,
    "minResTime" : 21.0,
    "maxResTime" : 21.0,
    "pct1ResTime" : 21.0,
    "pct2ResTime" : 21.0,
    "pct3ResTime" : 21.0,
    "throughput" : 47.61904761904761,
    "receivedKBytesPerSec" : 0.0,
    "sentKBytesPerSec" : 0.0
  },
  "1.0 Login" : {
    "transaction" : "1.0 Login",
    "sampleCount" : 3329,
    "errorCount" : 0,
    "errorPct" : 0.0,
    "meanResTime" : 2474.9396215079587,
    "medianResTime" : 1095.0,
    "minResTime" : 332.0,
    "maxResTime" : 27144.0,
    "pct1ResTime" : 5473.0,
    "pct2ResTime" : 11159.5,
    "pct3ResTime" : 14116.099999999951,
    "throughput" : 0.9259635277736209,
    "receivedKBytesPerSec" : 241.57109913612666,
    "sentKBytesPerSec" : 27.636192817093136
  },
  "4.0 Vaccination for menacwy" : {
    "transaction" : "4.0 Vaccination for menacwy",
    "sampleCount" : 382,
    "errorCount" : 2,
    "errorPct" : 0.5235602,
    "meanResTime" : 905.8429319371736,
    "medianResTime" : 876.0,
    "minResTime" : 251.0,
    "maxResTime" : 1929.0,
    "pct1ResTime" : 1162.4,
    "pct2ResTime" : 1282.55,
    "pct3ResTime" : 1776.19,
    "throughput" : 0.11053656532219094,
    "receivedKBytesPerSec" : 5.911485159670359,
    "sentKBytesPerSec" : 3.145482586512224
  },
  "7.0 Open Children Search" : {
    "transaction" : "7.0 Open Children Search",
    "sampleCount" : 1693,
    "errorCount" : 0,
    "errorPct" : 0.0,
    "meanResTime" : 1294.8198464264615,
    "medianResTime" : 786.0,
    "minResTime" : 86.0,
    "maxResTime" : 8986.0,
    "pct1ResTime" : 3632.6000000000004,
    "pct2ResTime" : 3921.3,
    "pct3ResTime" : 5120.66,
    "throughput" : 0.4718201052774737,
    "receivedKBytesPerSec" : 54.00170297569249,
    "sentKBytesPerSec" : 3.40289832760953
  },
  "Initialise vaccination list" : {
    "transaction" : "Initialise vaccination list",
    "sampleCount" : 1,
    "errorCount" : 0,
    "errorPct" : 0.0,
    "meanResTime" : 46.0,
    "medianResTime" : 46.0,
    "minResTime" : 46.0,
    "maxResTime" : 46.0,
    "pct1ResTime" : 46.0,
    "pct2ResTime" : 46.0,
    "pct3ResTime" : 46.0,
    "throughput" : 21.73913043478261,
    "receivedKBytesPerSec" : 6.241508152173913,
    "sentKBytesPerSec" : 13.41711956521739
  },
  "7.8 Year group search" : {
    "transaction" : "7.8 Year group search",
    "sampleCount" : 199,
    "errorCount" : 0,
    "errorPct" : 0.0,
    "meanResTime" : 1566.2814070351765,
    "medianResTime" : 1481.0,
    "minResTime" : 1311.0,
    "maxResTime" : 5115.0,
    "pct1ResTime" : 1721.0,
    "pct2ResTime" : 2201.0,
    "pct3ResTime" : 3058.0,
    "throughput" : 0.05755405670780962,
    "receivedKBytesPerSec" : 7.948929629663505,
    "sentKBytesPerSec" : 0.43821306746781524
  },
  "7.9 DOB search" : {
    "transaction" : "7.9 DOB search",
    "sampleCount" : 167,
    "errorCount" : 0,
    "errorPct" : 0.0,
    "meanResTime" : 1091.2095808383235,
    "medianResTime" : 993.0,
    "minResTime" : 675.0,
    "maxResTime" : 3257.0,
    "pct1ResTime" : 1451.6000000000001,
    "pct2ResTime" : 1810.9999999999993,
    "pct3ResTime" : 3210.7599999999993,
    "throughput" : 0.049239209978989305,
    "receivedKBytesPerSec" : 6.765222648669243,
    "sentKBytesPerSec" : 0.3709923162139116
  },
  "7.4 Partial name search" : {
    "transaction" : "7.4 Partial name search",
    "sampleCount" : 187,
    "errorCount" : 0,
    "errorPct" : 0.0,
    "meanResTime" : 1763.2887700534764,
    "medianResTime" : 949.0,
    "minResTime" : 227.0,
    "maxResTime" : 8895.0,
    "pct1ResTime" : 4557.6,
    "pct2ResTime" : 5108.2,
    "pct3ResTime" : 8829.880000000001,
    "throughput" : 0.053299556046050814,
    "receivedKBytesPerSec" : 7.203330008227228,
    "sentKBytesPerSec" : 0.39289077668640365
  },
  "Debug Sampler" : {
    "transaction" : "Debug Sampler",
    "sampleCount" : 1623,
    "errorCount" : 0,
    "errorPct" : 0.0,
    "meanResTime" : 0.29390018484288377,
    "medianResTime" : 0.0,
    "minResTime" : 0.0,
    "maxResTime" : 14.0,
    "pct1ResTime" : 1.0,
    "pct2ResTime" : 1.0,
    "pct3ResTime" : 1.0,
    "throughput" : 0.45483384972715574,
    "receivedKBytesPerSec" : 2.617569144536137,
    "sentKBytesPerSec" : 0.0
  },
  "Total" : {
    "transaction" : "Total",
    "sampleCount" : 29349,
    "errorCount" : 16,
    "errorPct" : 0.054516338,
    "meanResTime" : 545.0994582438884,
    "medianResTime" : 228.0,
    "minResTime" : 0.0,
    "maxResTime" : 60006.0,
    "pct1ResTime" : 1349.0,
    "pct2ResTime" : 2625.5500000000065,
    "pct3ResTime" : 4148.970000000005,
    "throughput" : 7.818983433580469,
    "receivedKBytesPerSec" : 424.62495823961115,
    "sentKBytesPerSec" : 61.183944936679396
  },
  "1.4 Open Sessions list" : {
    "transaction" : "1.4 Open Sessions list",
    "sampleCount" : 1630,
    "errorCount" : 0,
    "errorPct" : 0.0,
    "meanResTime" : 540.2601226993875,
    "medianResTime" : 529.5,
    "minResTime" : 322.0,
    "maxResTime" : 1751.0,
    "pct1ResTime" : 692.0,
    "pct2ResTime" : 756.4499999999998,
    "pct3ResTime" : 895.3800000000001,
    "throughput" : 0.45435996012782287,
    "receivedKBytesPerSec" : 37.50247590681398,
    "sentKBytesPerSec" : 3.2762387781103866
  },
  "Reset vaccination list" : {
    "transaction" : "Reset vaccination list",
    "sampleCount" : 1,
    "errorCount" : 0,
    "errorPct" : 0.0,
    "meanResTime" : 3.0,
    "medianResTime" : 3.0,
    "minResTime" : 3.0,
    "maxResTime" : 3.0,
    "pct1ResTime" : 3.0,
    "pct2ResTime" : 3.0,
    "pct3ResTime" : 3.0,
    "throughput" : 333.3333333333333,
    "receivedKBytesPerSec" : 95.37760416666667,
    "sentKBytesPerSec" : 204.75260416666666
  },
  "4.2 Vaccination batch" : {
    "transaction" : "4.2 Vaccination batch",
    "sampleCount" : 1580,
    "errorCount" : 6,
    "errorPct" : 0.37974682,
    "meanResTime" : 143.78227848101287,
    "medianResTime" : 117.0,
    "minResTime" : 69.0,
    "maxResTime" : 1201.0,
    "pct1ResTime" : 233.0,
    "pct2ResTime" : 292.9499999999998,
    "pct3ResTime" : 453.0400000000009,
    "throughput" : 0.45133430703473076,
    "receivedKBytesPerSec" : 7.261702928527641,
    "sentKBytesPerSec" : 4.001471741723371
  },
  "7.5 Needs Consent search" : {
    "transaction" : "7.5 Needs Consent search",
    "sampleCount" : 183,
    "errorCount" : 1,
    "errorPct" : 0.5464481,
    "meanResTime" : 4127.4098360655735,
    "medianResTime" : 3726.0,
    "minResTime" : 3389.0,
    "maxResTime" : 60006.0,
    "pct1ResTime" : 4253.4,
    "pct2ResTime" : 4379.999999999999,
    "pct3ResTime" : 13896.719999999812,
    "throughput" : 0.05213407859426012,
    "receivedKBytesPerSec" : 7.123377687362187,
    "sentKBytesPerSec" : 0.39378294658322366
  },
  "2.2 Session register" : {
    "transaction" : "2.2 Session register",
    "sampleCount" : 1624,
    "errorCount" : 0,
    "errorPct" : 0.0,
    "meanResTime" : 138.66687192118204,
    "medianResTime" : 100.0,
    "minResTime" : 58.0,
    "maxResTime" : 1196.0,
    "pct1ResTime" : 272.0,
    "pct2ResTime" : 343.0,
    "pct3ResTime" : 521.0,
    "throughput" : 0.4538837101863075,
    "receivedKBytesPerSec" : 18.312326203972656,
    "sentKBytesPerSec" : 3.280392919812387
  },
  "7.6 Needs triage search" : {
    "transaction" : "7.6 Needs triage search",
    "sampleCount" : 187,
    "errorCount" : 0,
    "errorPct" : 0.0,
    "meanResTime" : 215.5614973262032,
    "medianResTime" : 187.0,
    "minResTime" : 130.0,
    "maxResTime" : 792.0,
    "pct1ResTime" : 316.20000000000005,
    "pct2ResTime" : 362.79999999999995,
    "pct3ResTime" : 731.2800000000003,
    "throughput" : 0.053098556315562165,
    "receivedKBytesPerSec" : 3.5278409843939933,
    "sentKBytesPerSec" : 0.40271581368710413
  },
  "7.3 Last name search" : {
    "transaction" : "7.3 Last name search",
    "sampleCount" : 178,
    "errorCount" : 0,
    "errorPct" : 0.0,
    "meanResTime" : 1292.4887640449426,
    "medianResTime" : 803.5,
    "minResTime" : 300.0,
    "maxResTime" : 5608.0,
    "pct1ResTime" : 3191.499999999999,
    "pct2ResTime" : 4137.549999999999,
    "pct3ResTime" : 5558.2300000000005,
    "throughput" : 0.05213298597534813,
    "receivedKBytesPerSec" : 7.089854990488659,
    "sentKBytesPerSec" : 0.3844473075179866
  }
}