{
  "Prevent multiple runs" : {
    "transaction" : "Prevent multiple runs",
    "sampleCount" : 1,
    "errorCount" : 0,
    "errorPct" : 0.0,
    "meanResTime" : 19.0,
    "medianResTime" : 19.0,
    "minResTime" : 19.0,
    "maxResTime" : 19.0,
    "pct1ResTime" : 19.0,
    "pct2ResTime" : 19.0,
    "pct3ResTime" : 19.0,
    "throughput" : 52.63157894736842,
    "receivedKBytesPerSec" : 0.0,
    "sentKBytesPerSec" : 0.0
  },
  "2.0 Register attendance" : {
    "transaction" : "2.0 Register attendance",
    "sampleCount" : 756,
    "errorCount" : 0,
    "errorPct" : 0.0,
    "meanResTime" : 6528.035714285709,
    "medianResTime" : 6277.0,
    "minResTime" : 3944.0,
    "maxResTime" : 11531.0,
    "pct1ResTime" : 8086.500000000003,
    "pct2ResTime" : 8985.199999999999,
    "pct3ResTime" : 10637.929999999993,
    "throughput" : 0.21556087170991667,
    "receivedKBytesPerSec" : 65.15630802910785,
    "sentKBytesPerSec" : 0.9357246545786726
  },
  "Completed sessions list" : {
    "transaction" : "Completed sessions list",
    "sampleCount" : 1,
    "errorCount" : 0,
    "errorPct" : 0.0,
    "meanResTime" : 319.0,
    "medianResTime" : 319.0,
    "minResTime" : 319.0,
    "maxResTime" : 319.0,
    "pct1ResTime" : 319.0,
    "pct2ResTime" : 319.0,
    "pct3ResTime" : 319.0,
    "throughput" : 3.134796238244514,
    "receivedKBytesPerSec" : 43.498359130094045,
    "sentKBytesPerSec" : 1.9041438087774294
  },
  "1.4 Select Organisations" : {
    "transaction" : "1.4 Select Organisations",
    "sampleCount" : 70,
    "errorCount" : 0,
    "errorPct" : 0.0,
    "meanResTime" : 431.9571428571428,
    "medianResTime" : 407.5,
    "minResTime" : 378.0,
    "maxResTime" : 740.0,
    "pct1ResTime" : 518.1,
    "pct2ResTime" : 570.3000000000001,
    "pct3ResTime" : 740.0,
    "throughput" : 0.07832719956763386,
    "receivedKBytesPerSec" : 1.1270243734663254,
    "sentKBytesPerSec" : 0.11320728062509582
  },
  "Scheduled sessions list" : {
    "transaction" : "Scheduled sessions list",
    "sampleCount" : 1,
    "errorCount" : 0,
    "errorPct" : 0.0,
    "meanResTime" : 308.0,
    "medianResTime" : 308.0,
    "minResTime" : 308.0,
    "maxResTime" : 308.0,
    "pct1ResTime" : 308.0,
    "pct2ResTime" : 308.0,
    "pct3ResTime" : 308.0,
    "throughput" : 3.246753246753247,
    "receivedKBytesPerSec" : 42.090477881493506,
    "sentKBytesPerSec" : 1.9721489448051948
  },
  "2.3 Search by first/last name" : {
    "transaction" : "2.3 Search by first/last name",
    "sampleCount" : 757,
    "errorCount" : 0,
    "errorPct" : 0.0,
    "meanResTime" : 1412.8097754293262,
    "medianResTime" : 1277.0,
    "minResTime" : 927.0,
    "maxResTime" : 6424.0,
    "pct1ResTime" : 1906.2,
    "pct2ResTime" : 2308.8,
    "pct3ResTime" : 3163.999999999992,
    "throughput" : 0.21595228395928115,
    "receivedKBytesPerSec" : 20.604189920940637,
    "sentKBytesPerSec" : 0.18627489156741991
  },
  "5.8 Consent confirm" : {
    "transaction" : "5.8 Consent confirm",
    "sampleCount" : 2,
    "errorCount" : 0,
    "errorPct" : 0.0,
    "meanResTime" : 916.5,
    "medianResTime" : 916.5,
    "minResTime" : 875.0,
    "maxResTime" : 958.0,
    "pct1ResTime" : 958.0,
    "pct2ResTime" : 958.0,
    "pct3ResTime" : 958.0,
    "throughput" : 0.011338961237761009,
    "receivedKBytesPerSec" : 0.9284715735785194,
    "sentKBytesPerSec" : 0.02493131955744034
  },
  "5.9 Patient return to td_ipv vaccination page" : {
    "transaction" : "5.9 Patient return to td_ipv vaccination page",
    "sampleCount" : 499,
    "errorCount" : 0,
    "errorPct" : 0.0,
    "meanResTime" : 554.9158316633268,
    "medianResTime" : 487.0,
    "minResTime" : 327.0,
    "maxResTime" : 2131.0,
    "pct1ResTime" : 775.0,
    "pct2ResTime" : 988.0,
    "pct3ResTime" : 1479.0,
    "throughput" : 0.1524834170464237,
    "receivedKBytesPerSec" : 4.4867440339526174,
    "sentKBytesPerSec" : 0.10618835155036521
  },
  "1.2 Sign-in page" : {
    "transaction" : "1.2 Sign-in page",
    "sampleCount" : 70,
    "errorCount" : 0,
    "errorPct" : 0.0,
    "meanResTime" : 97.7142857142857,
    "medianResTime" : 92.5,
    "minResTime" : 89.0,
    "maxResTime" : 334.0,
    "pct1ResTime" : 102.8,
    "pct2ResTime" : 111.60000000000002,
    "pct3ResTime" : 334.0,
    "throughput" : 0.07892793315931604,
    "receivedKBytesPerSec" : 0.47726734582273916,
    "sentKBytesPerSec" : 0.047557162850876945
  },
  "3.0 Nurse triage" : {
    "transaction" : "3.0 Nurse triage",
    "sampleCount" : 1711,
    "errorCount" : 0,
    "errorPct" : 0.0,
    "meanResTime" : 1976.1355932203385,
    "medianResTime" : 1818.0,
    "minResTime" : 1200.0,
    "maxResTime" : 7735.0,
    "pct1ResTime" : 2572.0,
    "pct2ResTime" : 3051.399999999996,
    "pct3ResTime" : 4404.039999999994,
    "throughput" : 0.4943128026438079,
    "receivedKBytesPerSec" : 61.94295126302554,
    "sentKBytesPerSec" : 1.486703173395744
  },
  "2.4 Patient attending session" : {
    "transaction" : "2.4 Patient attending session",
    "sampleCount" : 748,
    "errorCount" : 0,
    "errorPct" : 0.0,
    "meanResTime" : 1712.4852941176466,
    "medianResTime" : 1547.0,
    "minResTime" : 1104.0,
    "maxResTime" : 5393.0,
    "pct1ResTime" : 2378.4,
    "pct2ResTime" : 2774.899999999999,
    "pct3ResTime" : 4128.59,
    "throughput" : 0.21372301782615688,
    "receivedKBytesPerSec" : 17.54367409466658,
    "sentKBytesPerSec" : 0.31766253235489333
  },
  "5.4 Consent route" : {
    "transaction" : "5.4 Consent route",
    "sampleCount" : 2,
    "errorCount" : 0,
    "errorPct" : 0.0,
    "meanResTime" : 547.5,
    "medianResTime" : 547.5,
    "minResTime" : 460.0,
    "maxResTime" : 635.0,
    "pct1ResTime" : 635.0,
    "pct2ResTime" : 635.0,
    "pct3ResTime" : 635.0,
    "throughput" : 0.010973936899862827,
    "receivedKBytesPerSec" : 0.12509645061728394,
    "sentKBytesPerSec" : 0.017355752743484224
  },
  "1.1 Homepage" : {
    "transaction" : "1.1 Homepage",
    "sampleCount" : 70,
    "errorCount" : 0,
    "errorPct" : 0.0,
    "meanResTime" : 294.92857142857133,
    "medianResTime" : 274.0,
    "minResTime" : 259.0,
    "maxResTime" : 743.0,
    "pct1ResTime" : 350.0,
    "pct2ResTime" : 375.9000000000001,
    "pct3ResTime" : 743.0,
    "throughput" : 0.07890373406285472,
    "receivedKBytesPerSec" : 0.40885079388428425,
    "sentKBytesPerSec" : 0.042765207426644886
  },
  "1.3 Sign-in" : {
    "transaction" : "1.3 Sign-in",
    "sampleCount" : 70,
    "errorCount" : 0,
    "errorPct" : 0.0,
    "meanResTime" : 528.6714285714287,
    "medianResTime" : 494.0,
    "minResTime" : 449.0,
    "maxResTime" : 993.0,
    "pct1ResTime" : 650.1,
    "pct2ResTime" : 774.7000000000003,
    "pct3ResTime" : 993.0,
    "throughput" : 0.07845704140738483,
    "receivedKBytesPerSec" : 0.7629640804050177,
    "sentKBytesPerSec" : 0.12343192744853218
  },
  "Get school name" : {
    "transaction" : "Get school name",
    "sampleCount" : 1,
    "errorCount" : 0,
    "errorPct" : 0.0,
    "meanResTime" : 6763.0,
    "medianResTime" : 6763.0,
    "minResTime" : 6763.0,
    "maxResTime" : 6763.0,
    "pct1ResTime" : 6763.0,
    "pct2ResTime" : 6763.0,
    "pct3ResTime" : 6763.0,
    "throughput" : 0.1478633742422002,
    "receivedKBytesPerSec" : 1469.6804995933758,
    "sentKBytesPerSec" : 0.09255900672778353
  },
  "2.1 Open session" : {
    "transaction" : "2.1 Open session",
    "sampleCount" : 762,
    "errorCount" : 0,
    "errorPct" : 0.0,
    "meanResTime" : 1489.7112860892387,
    "medianResTime" : 1313.5,
    "minResTime" : 781.0,
    "maxResTime" : 4626.0,
    "pct1ResTime" : 2169.1000000000004,
    "pct2ResTime" : 2642.8,
    "pct3ResTime" : 3799.4800000000005,
    "throughput" : 0.21572529846246183,
    "receivedKBytesPerSec" : 3.57847576151455,
    "sentKBytesPerSec" : 0.14117603552389824
  },
  "3.3 Nurse triage complete" : {
    "transaction" : "3.3 Nurse triage complete",
    "sampleCount" : 1703,
    "errorCount" : 0,
    "errorPct" : 0.0,
    "meanResTime" : 518.6283029947164,
    "medianResTime" : 425.0,
    "minResTime" : 329.0,
    "maxResTime" : 5993.0,
    "pct1ResTime" : 702.8000000000004,
    "pct2ResTime" : 982.799999999999,
    "pct3ResTime" : 1850.8400000000001,
    "throughput" : 0.4938500731495484,
    "receivedKBytesPerSec" : 11.968718497755491,
    "sentKBytesPerSec" : 0.3347260738810439
  },
  "4.3 Vaccination confirm" : {
    "transaction" : "4.3 Vaccination confirm",
    "sampleCount" : 1673,
    "errorCount" : 0,
    "errorPct" : 0.0,
    "meanResTime" : 1301.4955170352648,
    "medianResTime" : 1185.0,
    "minResTime" : 841.0,
    "maxResTime" : 5149.0,
    "pct1ResTime" : 1766.6000000000001,
    "pct2ResTime" : 2158.0999999999995,
    "pct3ResTime" : 3457.279999999999,
    "throughput" : 0.49839102812736646,
    "receivedKBytesPerSec" : 12.996691877883324,
    "sentKBytesPerSec" : 1.160318357881996
  },
  "5.6 Consent questions" : {
    "transaction" : "5.6 Consent questions",
    "sampleCount" : 2,
    "errorCount" : 0,
    "errorPct" : 0.0,
    "meanResTime" : 458.0,
    "medianResTime" : 458.0,
    "minResTime" : 417.0,
    "maxResTime" : 499.0,
    "pct1ResTime" : 499.0,
    "pct2ResTime" : 499.0,
    "pct3ResTime" : 499.0,
    "throughput" : 0.011219503985728792,
    "receivedKBytesPerSec" : 0.1350175269688827,
    "sentKBytesPerSec" : 0.022050050557889837
  },
  "4.1 Vaccination questions" : {
    "transaction" : "4.1 Vaccination questions",
    "sampleCount" : 1721,
    "errorCount" : 36,
    "errorPct" : 2.0918071,
    "meanResTime" : 635.6728646135961,
    "medianResTime" : 600.0,
    "minResTime" : 94.0,
    "maxResTime" : 4619.0,
    "pct1ResTime" : 828.5999999999999,
    "pct2ResTime" : 1048.6999999999982,
    "pct3ResTime" : 2101.0199999999995,
    "throughput" : 0.5047059948280099,
    "receivedKBytesPerSec" : 5.788772453514848,
    "sentKBytesPerSec" : 1.076346741211488
  },
  "5.3 Consent parent details" : {
    "transaction" : "5.3 Consent parent details",
    "sampleCount" : 2,
    "errorCount" : 0,
    "errorPct" : 0.0,
    "meanResTime" : 751.0,
    "medianResTime" : 751.0,
    "minResTime" : 434.0,
    "maxResTime" : 1068.0,
    "pct1ResTime" : 1068.0,
    "pct2ResTime" : 1068.0,
    "pct3ResTime" : 1068.0,
    "throughput" : 0.01097309397357679,
    "receivedKBytesPerSec" : 0.12431529608150814,
    "sentKBytesPerSec" : 0.018565317684786902
  },
  "3.1 Nurse triage new" : {
    "transaction" : "3.1 Nurse triage new",
    "sampleCount" : 1718,
    "errorCount" : 0,
    "errorPct" : 0.0,
    "meanResTime" : 431.22118742724075,
    "medianResTime" : 362.0,
    "minResTime" : 291.0,
    "maxResTime" : 3322.0,
    "pct1ResTime" : 556.0,
    "pct2ResTime" : 671.2499999999998,
    "pct3ResTime" : 1545.5899999999979,
    "throughput" : 0.4934821860973602,
    "receivedKBytesPerSec" : 5.5505528340648915,
    "sentKBytesPerSec" : 0.3402622888877176
  },
  "3.2 Nurse triage result" : {
    "transaction" : "3.2 Nurse triage result",
    "sampleCount" : 1711,
    "errorCount" : 0,
    "errorPct" : 0.0,
    "meanResTime" : 1028.388077147868,
    "medianResTime" : 923.0,
    "minResTime" : 596.0,
    "maxResTime" : 4340.0,
    "pct1ResTime" : 1349.0,
    "pct2ResTime" : 1741.3999999999999,
    "pct3ResTime" : 2973.879999999997,
    "throughput" : 0.49418687773539366,
    "receivedKBytesPerSec" : 44.447814219527,
    "sentKBytesPerSec" : 0.8121881839838105
  },
  "5.2 Consent who" : {
    "transaction" : "5.2 Consent who",
    "sampleCount" : 2,
    "errorCount" : 0,
    "errorPct" : 0.0,
    "meanResTime" : 685.5,
    "medianResTime" : 685.5,
    "minResTime" : 497.0,
    "maxResTime" : 874.0,
    "pct1ResTime" : 874.0,
    "pct2ResTime" : 874.0,
    "pct3ResTime" : 874.0,
    "throughput" : 0.011199023445155581,
    "receivedKBytesPerSec" : 0.16798535167733375,
    "sentKBytesPerSec" : 0.017722673332885373
  },
  "1.0 Login" : {
    "transaction" : "1.0 Login",
    "sampleCount" : 70,
    "errorCount" : 0,
    "errorPct" : 0.0,
    "meanResTime" : 1817.8285714285716,
    "medianResTime" : 1654.5,
    "minResTime" : 1497.0,
    "maxResTime" : 9366.0,
    "pct1ResTime" : 2035.6,
    "pct2ResTime" : 2170.3,
    "pct3ResTime" : 9366.0,
    "throughput" : 0.07875734412233941,
    "receivedKBytesPerSec" : 14.918415434231429,
    "sentKBytesPerSec" : 0.3770145267218043
  },
  "5.0 Consent" : {
    "transaction" : "5.0 Consent",
    "sampleCount" : 2,
    "errorCount" : 0,
    "errorPct" : 0.0,
    "meanResTime" : 5657.0,
    "medianResTime" : 5657.0,
    "minResTime" : 5590.0,
    "maxResTime" : 5724.0,
    "pct1ResTime" : 5724.0,
    "pct2ResTime" : 5724.0,
    "pct3ResTime" : 5724.0,
    "throughput" : 0.010826084367675477,
    "receivedKBytesPerSec" : 2.2031081688219594,
    "sentKBytesPerSec" : 0.16417799232971922
  },
  "5.9 Patient return to menacwy vaccination page" : {
    "transaction" : "5.9 Patient return to menacwy vaccination page",
    "sampleCount" : 517,
    "errorCount" : 0,
    "errorPct" : 0.0,
    "meanResTime" : 581.7021276595743,
    "medianResTime" : 521.0,
    "minResTime" : 331.0,
    "maxResTime" : 6040.0,
    "pct1ResTime" : 779.0,
    "pct2ResTime" : 980.3999999999995,
    "pct3ResTime" : 1908.0600000000068,
    "throughput" : 0.15454481321301355,
    "receivedKBytesPerSec" : 4.5013097682261245,
    "sentKBytesPerSec" : 0.10777425753846881
  },
  "4.0 Vaccination" : {
    "transaction" : "4.0 Vaccination",
    "sampleCount" : 1720,
    "errorCount" : 36,
    "errorPct" : 2.0930233,
    "meanResTime" : 2456.7052325581353,
    "medianResTime" : 2311.0,
    "minResTime" : 95.0,
    "maxResTime" : 7122.0,
    "pct1ResTime" : 3158.0,
    "pct2ResTime" : 3737.699999999999,
    "pct3ResTime" : 5424.5999999999985,
    "throughput" : 0.4997682760464261,
    "receivedKBytesPerSec" : 26.451244183746926,
    "sentKBytesPerSec" : 2.988752081157138
  },
  "2.5 Patient return to consent page" : {
    "transaction" : "2.5 Patient return to consent page",
    "sampleCount" : 745,
    "errorCount" : 0,
    "errorPct" : 0.0,
    "meanResTime" : 549.2617449664424,
    "medianResTime" : 447.0,
    "minResTime" : 323.0,
    "maxResTime" : 3313.0,
    "pct1ResTime" : 774.4,
    "pct2ResTime" : 955.4999999999997,
    "pct3ResTime" : 2125.0999999999976,
    "throughput" : 0.21482456762590882,
    "receivedKBytesPerSec" : 4.707144812357949,
    "sentKBytesPerSec" : 0.1489506279437454
  },
  "5.5 Consent agree" : {
    "transaction" : "5.5 Consent agree",
    "sampleCount" : 2,
    "errorCount" : 0,
    "errorPct" : 0.0,
    "meanResTime" : 507.5,
    "medianResTime" : 507.5,
    "minResTime" : 454.0,
    "maxResTime" : 561.0,
    "pct1ResTime" : 561.0,
    "pct2ResTime" : 561.0,
    "pct3ResTime" : 561.0,
    "throughput" : 0.011353379617277573,
    "receivedKBytesPerSec" : 0.19739247462519657,
    "sentKBytesPerSec" : 0.01774519929438746
  },
  "Debug Sampler" : {
    "transaction" : "Debug Sampler",
    "sampleCount" : 1942,
    "errorCount" : 0,
    "errorPct" : 0.0,
    "meanResTime" : 0.24768280123583897,
    "medianResTime" : 0.0,
    "minResTime" : 0.0,
    "maxResTime" : 15.0,
    "pct1ResTime" : 1.0,
    "pct2ResTime" : 1.0,
    "pct3ResTime" : 1.0,
    "throughput" : 0.5528016683110286,
    "receivedKBytesPerSec" : 2.1797430279063787,
    "sentKBytesPerSec" : 0.0
  },
  "1.5 Open Sessions list" : {
    "transaction" : "1.5 Open Sessions list",
    "sampleCount" : 243,
    "errorCount" : 0,
    "errorPct" : 0.0,
    "meanResTime" : 404.7448559670783,
    "medianResTime" : 344.0,
    "minResTime" : 297.0,
    "maxResTime" : 2214.0,
    "pct1ResTime" : 527.4,
    "pct2ResTime" : 600.5999999999999,
    "pct3ResTime" : 1107.1600000000003,
    "throughput" : 0.06851524365486814,
    "receivedKBytesPerSec" : 0.801976279733642,
    "sentKBytesPerSec" : 0.04347322387976167
  },
  "Total" : {
    "transaction" : "Total",
    "sampleCount" : 17484,
    "errorCount" : 36,
    "errorPct" : 0.20590255,
    "meanResTime" : 763.476035232211,
    "medianResTime" : 602.0,
    "minResTime" : 0.0,
    "maxResTime" : 6763.0,
    "pct1ResTime" : 1468.0,
    "pct2ResTime" : 1786.75,
    "pct3ResTime" : 2806.0,
    "throughput" : 4.855637541265559,
    "receivedKBytesPerSec" : 162.3700019989687,
    "sentKBytesPerSec" : 5.52865624851594
  },
  "4.2 Vaccination batch" : {
    "transaction" : "4.2 Vaccination batch",
    "sampleCount" : 1684,
    "errorCount" : 0,
    "errorPct" : 0.0,
    "meanResTime" : 566.9340855106889,
    "medianResTime" : 486.0,
    "minResTime" : 406.0,
    "maxResTime" : 4055.0,
    "pct1ResTime" : 732.0,
    "pct2ResTime" : 954.75,
    "pct3ResTime" : 1816.15,
    "throughput" : 0.49469030448129486,
    "receivedKBytesPerSec" : 8.131134515958463,
    "sentKBytesPerSec" : 0.7999088658328805
  },
  "5.7 Consent triage" : {
    "transaction" : "5.7 Consent triage",
    "sampleCount" : 2,
    "errorCount" : 0,
    "errorPct" : 0.0,
    "meanResTime" : 605.5,
    "medianResTime" : 605.5,
    "minResTime" : 469.0,
    "maxResTime" : 742.0,
    "pct1ResTime" : 742.0,
    "pct2ResTime" : 742.0,
    "pct3ResTime" : 742.0,
    "throughput" : 0.011507413651244814,
    "receivedKBytesPerSec" : 0.1880237221736354,
    "sentKBytesPerSec" : 0.019312002304359584
  },
  "2.2 Session register" : {
    "transaction" : "2.2 Session register",
    "sampleCount" : 760,
    "errorCount" : 0,
    "errorPct" : 0.0,
    "meanResTime" : 1388.2776315789467,
    "medianResTime" : 1288.5,
    "minResTime" : 709.0,
    "maxResTime" : 4787.0,
    "pct1ResTime" : 1783.6,
    "pct2ResTime" : 2235.199999999999,
    "pct3ResTime" : 3071.0899999999983,
    "throughput" : 0.2155135745194898,
    "receivedKBytesPerSec" : 18.004979730469792,
    "sentKBytesPerSec" : 0.14292894379207477
  },
  "5.1 Consent homepage" : {
    "transaction" : "5.1 Consent homepage",
    "sampleCount" : 2,
    "errorCount" : 0,
    "errorPct" : 0.0,
    "meanResTime" : 682.0,
    "medianResTime" : 682.0,
    "minResTime" : 624.0,
    "maxResTime" : 740.0,
    "pct1ResTime" : 740.0,
    "pct2ResTime" : 740.0,
    "pct3ResTime" : 740.0,
    "throughput" : 0.011019344459198123,
    "receivedKBytesPerSec" : 0.13888786060804742,
    "sentKBytesPerSec" : 0.023749700411572518
  },
  "Calculate slug" : {
    "transaction" : "Calculate slug",
    "sampleCount" : 1,
    "errorCount" : 0,
    "errorPct" : 0.0,
    "meanResTime" : 60.0,
    "medianResTime" : 60.0,
    "minResTime" : 60.0,
    "maxResTime" : 60.0,
    "pct1ResTime" : 60.0,
    "pct2ResTime" : 60.0,
    "pct3ResTime" : 60.0,
    "throughput" : 16.666666666666668,
    "receivedKBytesPerSec" : 0.11393229166666667,
    "sentKBytesPerSec" : 0.0
  }
}